bibt/sentinelone/__init__.py
bibt/sentinelone/classes.py
bibt/sentinelone/params.py
bibt/sentinelone/version.py
bibt_sentinelone-0.0.5.dist-info/METADATA
bibt_sentinelone-0.0.5.dist-info/WHEEL
bibt_sentinelone-0.0.5.dist-info/licenses/LICENSE
bibt_sentinelone-0.0.5.dist-info/RECORD
