Metadata-Version: 2.3
Name: bibt-sentinelone
Version: 0.0.5
Summary: Functionality often used by BITS Blue Team (SentinelOne).
Project-URL: Bug Tracker, https://github.com/broadinstitute/bibt-sentinelone/issues
Project-URL: Documentation, https://bibt-sentinelone.readthedocs.io/en/latest/
Project-URL: Homepage, https://github.com/broadinstitute/bibt-sentinelone
Author-email: Matthew OBrien <mobrien@broadinstitute.org>
Classifier: License :: OSI Approved :: MIT License
Classifier: Operating System :: OS Independent
Classifier: Programming Language :: Python :: 3
Classifier: Programming Language :: Python :: 3.9
Classifier: Programming Language :: Python :: 3.10
Classifier: Programming Language :: Python :: 3.11
Classifier: Programming Language :: Python :: 3.12
Classifier: Topic :: Security
Classifier: Topic :: Software Development :: Libraries
Classifier: Topic :: Utilities
Requires-Python: >=3.7
Requires-Dist: glom==23.5.0
Requires-Dist: requests==2.31.0
